stringsim/__init__.py
stringsim/txtsim.py
strsim/__init__.py
strsim/txtsim.py
stringsim-0.0.2.dist-info/LICENSE
stringsim-0.0.2.dist-info/METADATA
stringsim-0.0.2.dist-info/WHEEL
stringsim-0.0.2.dist-info/top_level.txt
stringsim-0.0.2.dist-info/RECORD
