Metadata-Version: 2.1
Name: stringsim
Version: 0.0.2
Summary: A package that uses other algorithms for fuzzy matching
Home-page: https://github.com/arnavg115/stringsim
Author: Arnav G
Author-email: soccercream20@gmail.com
License: UNKNOWN
Platform: UNKNOWN
Classifier: Programming Language :: Python :: 3
Classifier: License :: OSI Approved :: MIT License
Classifier: Operating System :: OS Independent
Requires-Python: >=3.6
